{
    "@context": "https://schema.org",
    "@type": "Hospital",
    "@id": "https://hospitalhdr.com/#hospital",
    "name": "Hospital Dr. Raúl Hernández",
    "legalName": "Hospital Dr. Raúl Hernández S.A. de C.V.",
    "url": "https://hospitalhdr.com/",
    "logo": "https://hospitalhdr.com/logo.png",
    "image": "https://hospitalhdr.com/imagen-principal.jpg",
    "description": "Hospital privado en León, Guanajuato que ofrece servicios médicos especializados, atención 24 horas y diversas especialidades clínicas.",
    "telephone": "+52-477-714-1973",
    "email": "contabilidad@hospitalhdr.com",
    "priceRange": "$$",
    "address": {
        "@type": "PostalAddress",
        "streetAddress": "5 de Febrero 724",
        "addressLocality": "León",
        "addressRegion": "Guanajuato",
        "postalCode": "37000",
        "addressCountry": "MX"
    },
    "geo": {
        "@type": "GeoCoordinates",
        "latitude": null,
        "longitude": null
    },
    "openingHoursSpecification": [
        {
            "@type": "OpeningHoursSpecification",
            "dayOfWeek": [
                "Monday",
                "Tuesday",
                "Wednesday",
                "Thursday",
                "Friday",
                "Saturday",
                "Sunday"
            ],
            "opens": "00:00",
            "closes": "23:59"
        }
    ],
    "contactPoint": [
        {
            "@type": "ContactPoint",
            "telephone": "+52-477-714-1973",
            "contactType": "customer service",
            "areaServed": "MX",
            "availableLanguage": [
                "Spanish"
            ]
        }
    ],
    "sameAs": [
        "https://www.facebook.com/hospital.hdr.leon/"
    ],
    "medicalSpecialty": [
        "Ginecology",
        "Otolaryngology",
        "Ophthalmology",
        "Maxillofacial",
        "Genetics"
    ],
    "availableService": [
        {
            "@type": "MedicalProcedure",
            "name": "Cirugía general"
        },
        {
            "@type": "MedicalProcedure",
            "name": "Servicios hospitalarios especializados"
        }
    ],
    "founder": {
        "@type": "Person",
        "name": "José Raúl Hernández Torres"
    },
    "foundingDate": null,
    "aggregateRating": {
        "@type": "AggregateRating",
        "ratingValue": "3.8",
        "reviewCount": "121"
    }
}